nico/__init__.py
nico/modelos.py
teste_marinonigrande-0.0.1.dist-info/LICENSE
teste_marinonigrande-0.0.1.dist-info/METADATA
teste_marinonigrande-0.0.1.dist-info/WHEEL
teste_marinonigrande-0.0.1.dist-info/top_level.txt
teste_marinonigrande-0.0.1.dist-info/RECORD
